{
  "NetworkTables": {
    "Persistent Values": {
      "open": false
    },
    "Retained Values": {
      "open": false
    },
    "transitory": {
      "SmartDashboard": {
        "PID Rotation Controller: ": {
          "open": true
        },
        "open": true
      },
      "photonvision": {
        "Orange_Pi_Cam": {
          "open": true
        }
      }
    },
    "types": {
      "/FMSInfo": "FMSInfo",
      "/SmartDashboard/Field": "Field2d",
      "/SmartDashboard/PID Rotation Controller: ": "PIDController",
      "/SmartDashboard/PhotonAlerts": "Alerts"
    },
    "windows": {
      "/SmartDashboard/Field": {
        "Robot": {
          "arrowColor": [
            255.0,
            157.5,
            0.0,
            255.0
          ]
        },
        "bottom": 1914,
        "builtin": "",
        "height": 8.069275856018066,
        "image": "C:\\Users\\hcrt3\\Downloads\\2026-field.png",
        "left": 245,
        "right": 3942,
        "top": 118,
        "width": 16.54119300842285,
        "window": {
          "name": "Rebuilt-2026",
          "visible": true
        }
      }
    }
  },
  "NetworkTables Info": {
    "Connections": {
      "open": true
    },
    "visible": true
  },
  "NetworkTables Settings": {
    "mode": "Client (NT4)",
    "serverTeam": "3635"
  },
  "Plots": {
    "Plot <0>": {
      "plots": [
        {
          "backgroundColor": [
            0.0,
            0.0,
            0.0,
            0.8500000238418579
          ],
          "height": 142
        },
        {
          "backgroundColor": [
            0.05999999865889549,
            0.05999999865889549,
            0.05999999865889549,
            0.9399999976158142
          ],
          "height": 142
        }
      ],
      "window": {
        "visible": false
      }
    },
    "Plot <1>": {
      "plots": [
        {
          "backgroundColor": [
            0.05999999865889549,
            0.05999999865889549,
            0.05999999865889549,
            0.9399999976158142
          ],
          "height": 320,
          "legendLocation": 1
        }
      ],
      "window": {
        "visible": false
      }
    },
    "Plot <2>": {
      "plots": [
        {
          "backgroundColor": [
            0.05999999865889549,
            0.05999999865889549,
            0.05999999865889549,
            0.9399999976158142
          ],
          "height": 0,
          "series": [
            {
              "color": [
                0.2980392277240753,
                0.44705885648727417,
                0.6901960968971252,
                1.0
              ],
              "id": "NT:/SmartDashboard/PID Rotation Controller: /setpoint"
            },
            {
              "color": [
                0.8666667342185974,
                0.5176470875740051,
                0.32156863808631897,
                1.0
              ],
              "id": "NT:/SmartDashboard/PID Rotation Controller: /measurement"
            }
          ]
        }
      ],
      "window": {
        "name": "Rotation PID"
      }
    }
  }
}
